stopover_server/__init__.py
stopover_server/__main__.py
stopover_server/broker.py
stopover_server/partition.py
stopover_server/utils.py
stopover_server/version.py
stopover_server-2.2301.1.dist-info/METADATA
stopover_server-2.2301.1.dist-info/WHEEL
stopover_server-2.2301.1.dist-info/entry_points.txt
stopover_server-2.2301.1.dist-info/top_level.txt
stopover_server-2.2301.1.dist-info/RECORD
